cli_utils/__init__.py
cli_utils/netstat.py
isaac_cli_utils-0.1.0.dist-info/METADATA
isaac_cli_utils-0.1.0.dist-info/WHEEL
isaac_cli_utils-0.1.0.dist-info/entry_points.txt
isaac_cli_utils-0.1.0.dist-info/top_level.txt
isaac_cli_utils-0.1.0.dist-info/RECORD
