Metadata-Version: 2.2
Name: isaac_cli_utils
Version: 0.1.0
Summary: A collection of CLI utilities
Author: Isaac Harrison Gutekunst
Author-email: 
Requires-Dist: rich
Dynamic: author
Dynamic: requires-dist
Dynamic: summary
